setup.py
csp_validator/__init__.py
csp_validator/constant.py
csp_validator/csp.py
csp_validator.egg-info/PKG-INFO
csp_validator.egg-info/SOURCES.txt
csp_validator.egg-info/dependency_links.txt
csp_validator.egg-info/top_level.txt
tests/__init__.py
tests/test_functions.py
tests/test_host_source.py