Metadata-Version: 1.0
Name: csp-validator
Version: 0.3
Summary: Content-Security-Policy validator
Home-page: UNKNOWN
Author: Yeuk Hon Wong
Author-email: yeukhon@acm.org
License: UNKNOWN
Platform: UNKNOWN
Classifier: Programming Language :: Python :: 2.6
Classifier: Programming Language :: Python :: 2.7
Classifier: Topic :: Internet
Classifier: Topic :: Security
